README.md
setup.py
dta_utils_python/__init__.py
dta_utils_python/apikeys/__init__.py
dta_utils_python/apikeys/apikeys.py
dta_utils_python/base/__init__.py
dta_utils_python/base/api.py
dta_utils_python/secrets/__init__.py
dta_utils_python/secrets/secrets.py
totvs_dta_utils.egg-info/PKG-INFO
totvs_dta_utils.egg-info/SOURCES.txt
totvs_dta_utils.egg-info/dependency_links.txt
totvs_dta_utils.egg-info/requires.txt
totvs_dta_utils.egg-info/top_level.txt