Metadata-Version: 2.4
Name: totvs_dta_utils
Version: 1.4.14
Summary: Lib for integration with DTA services
Home-page: https://github.com/totvs-ai/dta-utils-python
Author: TOTVS - IDEIA
Author-email: info@totvs.ai
Requires-Python: >=3.10
Provides-Extra: secrets
Requires-Dist: python-dotenv>=1.0.0; extra == "secrets"
Requires-Dist: requests>=2.0.0; extra == "secrets"
Provides-Extra: apikeys
Requires-Dist: python-dotenv>=1.0.0; extra == "apikeys"
Requires-Dist: requests>=2.0.0; extra == "apikeys"
Dynamic: author
Dynamic: author-email
Dynamic: description
Dynamic: description-content-type
Dynamic: home-page
Dynamic: provides-extra
Dynamic: requires-python
Dynamic: summary
